python_cli/__init__.py
python_cli/hello.py
python_cli/main.py
python_cli_jbcorco85-0.1.13.dist-info/LICENSE
python_cli_jbcorco85-0.1.13.dist-info/METADATA
python_cli_jbcorco85-0.1.13.dist-info/WHEEL
python_cli_jbcorco85-0.1.13.dist-info/entry_points.txt
python_cli_jbcorco85-0.1.13.dist-info/RECORD
